{"course": {"name": "网球", "id": 14}, "topics": [{"type": 1, "info": "有司线员协助的情况下，当主裁看到明显错判时，也不可以对司线员进行更正", "index": 1, "solutions": [0], "options": ["错误", "正确"]}, {"type": 1, "info": "现代登山用铁锁多用为铝合金制成，承受冲击力在1500KG以上", "index": 2, "solutions": [0], "options": ["错误", "正确"]}, {"type": 1, "info": "溪降时已经涉水，故是否暴雨天均对活动影响不大", "index": 3, "solutions": [0], "options": ["错误", "正确"]}, {"type": 1, "info": "静脉出血血色为暗红，呈喷射状射出", "index": 4, "solutions": [0], "options": ["错误", "正确"]}, {"type": 1, "info": "救护中遇到受伤者较多时，应同等对待任何伤员，不论轻重", "index": 5, "solutions": [0], "options": ["错误", "正确"]}, {"type": 1, "info": "大型的综合性运动会由于比赛项目多、规模大、组织工作比较复杂，通常都是每二年举办一届", "index": 6, "solutions": [0], "options": ["错误", "正确"]}, {"type": 1, "info": "中国第一位奥运会女冠军是射击运动员栾菊杰", "index": 7, "solutions": [0], "options": ["错误", "正确"]}, {"type": 1, "info": "中国第一枚奥运会体操金牌的获得者是李小双", "index": 8, "solutions": [0], "options": ["错误", "正确"]}, {"type": 1, "info": "蛙泳时，身体自然伸直，俯卧水中，两臂向前伸直并拢、掌心向下、头略抬、身体纵轴与前进方向约45°角", "index": 9, "solutions": [0], "options": ["错误", "正确"]}, {"type": 1, "info": "短跑主要由有氧供能系统供能", "index": 10, "solutions": [0], "options": ["错误", "正确"]}, {"type": 1, "info": "丛林地区，大型兰科植物，风梨科植物等大叶植物的叶子与茎连接处有大的水", "index": 11, "solutions": [1], "options": ["错误", "正确"]}, {"type": 1, "info": "站立体前屈的测试，主要是检查受试者的柔韧素质", "index": 12, "solutions": [1], "options": ["错误", "正确"]}, {"type": 1, "info": "学生在进行游泳体育课的学习过程中，必须在教师的要求下完成各种练习，不得擅自进行一些有违反教学要求的技术动作.", "index": 13, "solutions": [1], "options": ["错误", "正确"]}, {"type": 1, "info": "编排原则是指在编排过程中应考虑的问题，其中心是要运动员创造优异成绩", "index": 14, "solutions": [0], "options": ["错误", "正确"]}, {"type": 1, "info": "蛙泳收腿应在接近结束时开始翻脚掌", "index": 15, "solutions": [1], "options": ["错误", "正确"]}, {"type": 1, "info": "双打中如果发出的球擦网而过，落地前触及接球方任一运动员，应判发球方得分", "index": 16, "solutions": [0], "options": ["错误", "正确"]}, {"type": 1, "info": "如果某运动员用球拍拦击对方击出的尚未过网的来球，则应判其失误，即过网击球", "index": 17, "solutions": [1], "options": ["错误", "正确"]}, {"type": 1, "info": "主裁执行临场裁判时，应边记分边报分", "index": 18, "solutions": [0], "options": ["错误", "正确"]}, {"type": 1, "info": "如果发球是从错误的半区发出的并且没有被察觉，那么由错误的发球所引起的比赛结果都将有效", "index": 19, "solutions": [1], "options": ["错误", "正确"]}, {"type": 1, "info": "如果一名运动员发球次序有误，此错误发现时该局已经结束，则后面的发球次序仍然按照原来的次序进行", "index": 20, "solutions": [0], "options": ["错误", "正确"]}, {"type": 1, "info": "裁判长可以在任何他认为有必要的时候，比如光线黑暗或场地条件或天气等原因而推延一场比赛", "index": 21, "solutions": [1], "options": ["错误", "正确"]}, {"type": 1, "info": "主裁判判定重赛，而运动员认为不应该重赛，对此主裁判认为他的裁定是最终裁定", "index": 22, "solutions": [0], "options": ["错误", "正确"]}, {"type": 1, "info": "发球队员发球过网未落地前，接球队员直接将击过网，发球队员把球抽出界外，判发球队员得分", "index": 23, "solutions": [1], "options": ["错误", "正确"]}, {"type": 1, "info": "在球被抛出准备发球的时候，发球员决定不击球而改用球拍接住球，这是一次发球失误", "index": 24, "solutions": [0], "options": ["错误", "正确"]}, {"type": 2, "options": ["自主性", "娱乐性", "集体性", "自发性"], "info": "体育就其本源而言，是人类与周围的生活环境相协调的一种( )行为", "index": 25, "solutions": [0]}, {"type": 2, "options": ["柔韧素质", "耐力素质", "灵巧素质", "速度素质"], "info": "人体有氧供能系统能力是下列哪项素质的基础？", "index": 26, "solutions": [1]}, {"type": 2, "options": ["手臂", "脚", "手和脚中间", "腰间"], "info": "向上攀登时你认为身体重心应一定要落在哪里？", "index": 27, "solutions": [2]}, {"type": 2, "options": ["大陆式", "筷子式", "握笔式", "台北式"], "info": "网球的基本握拍方法有东方式、西方式和", "index": 28, "solutions": [0]}, {"type": 2, "options": ["使伤者仰卧，松开领口、裤带和胸腹部衣物，清除口腔内异物", "急救者一手托住伤者下颌，使头后仰保持气道通畅", "另一手捏住伤者鼻孔，然后深吸一口气向伤者口内吹入，吹完后放开捏鼻孔的手", "每分钟16-18次左右，反复进行约2h"], "info": "下列对口对口人工呼吸描述不正确的是", "index": 29, "solutions": [3]}, {"type": 2, "options": ["10次", "3次", "1次", "5次"], "info": "一周最少运动几次对身体的最有益？", "index": 30, "solutions": [1]}, {"type": 2, "options": ["花样滑冰", "体操", "悬崖跳水", "电子竞技"], "info": "以下属于挑战类（冒险类）体育运动项目的是", "index": 31, "solutions": [2]}, {"type": 2, "options": ["每周1-2次", "每周2-3", "每周3-5", "每周5-7"], "info": "在安排有氧锻炼能力时要注意锻炼的频度，锻炼效果理想的频度是", "index": 32, "solutions": [2]}, {"type": 2, "options": ["运动前准备活动不充分", "运动情绪过于低下", "大脑氧债不断积累，并达到一定程度时", "空腹或带病进行剧烈运动"], "info": "造成运动中“极点”的原因是多方面的，其直接因素是", "index": 33, "solutions": [2]}, {"type": 2, "options": ["双手正握", "一正一反握", "双手反握", "随便"], "info": "双手握竿划桨时，应该是", "index": 34, "solutions": [1]}, {"type": 2, "options": ["人声", "哨子", "GPS", "对讲机"], "info": "在户外不可以用于联络通讯的是", "index": 35, "solutions": [2]}, {"type": 2, "options": ["云南", "四川", "广西", "广东"], "info": "我国下面哪个省没有丰富的洞穴资源", "index": 36, "solutions": [3]}, {"type": 2, "options": ["郑洁与晏紫", "李婷与孙甜甜", "李婷与李娜", "郑洁与李婷"], "info": "在雅典奥运会上（_____ ）夺得女双金牌，是中国在奥运会上获得的第一块网球奖牌，为中国网球运动取得历史性突破", "index": 37, "solutions": [1]}, {"type": 2, "options": ["全面发展身体素质", "掌握基本技术能力", "提高身体基本活动能力", "提高身体健康水平"], "info": "竞技体育欲最大限度地挖掘体力、智力与运动才能，以取得优异运动成绩，首先应建立的基础是", "index": 38, "solutions": [0]}, {"type": 2, "options": ["0.914", "1.07", "1.115", "1.37"], "info": "球柱的高度是（_____ ）米", "index": 39, "solutions": [1]}, {"type": 2, "options": ["7", "9", "11", "13"], "info": "进入抢7时，将进行的是第(_____ )局比赛", "index": 40, "solutions": [3]}, {"type": 2, "options": ["4", "6", "7", "13"], "info": "比赛采用长盘制时，一局至少需打（_____ ）分", "index": 41, "solutions": [0]}, {"type": 2, "options": ["兼终点端转身检查", "组长并记取分段成绩", "记录员", "转身检查长"], "info": "在人工计时和半人工计时的游泳比赛中，每个泳道有3名计时员分别被称作一表、二表、三表，除了计时的之外，他们各自有其他职责，其中一表为", "index": 42, "solutions": [1]}, {"type": 2, "options": ["横轴", "纵切面", "垂直轴", "纵轴"], "info": "根据人体在水中的运动方向，贯穿身体前后方向的轴叫做 _____ 轴？", "index": 43, "solutions": [3]}, {"type": 2, "options": ["球权", "场地", "要求对方选择", "以上都是"], "info": "赛前抽签得胜者有权首先选择", "index": 44, "solutions": [3]}, {"type": 2, "options": ["从身体小的部分到大的部分", "从身体大的部分到小的部分", "从身体正中的重心开始", "从头部往下开始"], "info": "在技术动作的产生过程中，最佳的生物力学的顺序依次为", "index": 45, "solutions": [1]}, {"type": 2, "options": ["稳定性为主", "深度为主", "力量为主"], "info": "初学底线正，反手技术时，应以击球时的", "index": 46, "solutions": [0]}, {"type": 2, "options": ["团结、和平、友谊、向困难挑战", "更快、更高、更强", "参与第一、胜利第二", "提高运动水平，不断进取，挑战自我"], "info": "奥林匹克运动会的格言是", "index": 47, "solutions": [1]}, {"type": 2, "options": ["1896，希腊", "1900，希腊", "1896，巴斯达", "1900，巴斯达"], "info": "第一届现代奥林匹克运动会是_____ 年在古奥运会发祥地 举行的", "index": 48, "solutions": [0]}, {"type": 2, "options": ["只能选择发球或接发球", "只能选择发球、接发球或场区", "选择发球、接发球、场区或要求对方选择", "既选择场区，又选择发球、接发球权"], "info": "在一场比赛的开始，抽签获胜方可以", "index": 49, "solutions": [2]}, {"type": 3, "options": ["直臂划手", "曲臂划手", "弯臂划手"], "info": "爬泳的划手形式一般有", "index": 50, "solutions": [0, 1]}], "sn": "ad6151e83c2db8de"}