{"course": {"name": "足球", "id": 29}, "topics": [{"type": 1, "info": "运动处方的主要内容是锻炼目的、适用人群、锻炼方法、运动负荷、运动频率、运动节奏。", "index": 1, "solutions": [1], "options": ["错误", "正确"]}, {"type": 1, "info": "湖泊是用面状地物符号来表示。", "index": 2, "solutions": [1], "options": ["错误", "正确"]}, {"type": 1, "info": "截线法是在线状地物上或一侧运动时采用。", "index": 3, "solutions": [1], "options": ["错误", "正确"]}, {"type": 1, "info": "造成脚底筋膜炎和神经刺痛的原因是由于经常提脚跟造成。", "index": 4, "solutions": [0], "options": ["错误", "正确"]}, {"type": 1, "info": "对照地图与实地的参照物，确定站立点与目标点，三者互为条件，有密切联系，三者没有固定的先后顺序，可根据具体情况决定。", "index": 5, "solutions": [1], "options": ["错误", "正确"]}, {"type": 1, "info": "在我国，大体上说，春秋季太阳出于东方，没于西方；夏季太阳出于东偏南，落于西偏南；冬季太阳出于东偏北而落于西偏北。", "index": 6, "solutions": [0], "options": ["错误", "正确"]}, {"type": 1, "info": "山背是同脉上由数个相邻山顶、鞍部交错连接的最高棱线。", "index": 7, "solutions": [0], "options": ["错误", "正确"]}, {"type": 1, "info": "利用太阳和手表判定方位是利用当地时间折半对太阳，12字头指北方来判断。", "index": 8, "solutions": [1], "options": ["错误", "正确"]}, {"type": 1, "info": "体育教学过程的三个阶段就是动作技能形成的三个阶段。", "index": 9, "solutions": [0], "options": ["错误", "正确"]}, {"type": 1, "info": "定向地图上的符号的构成要素包括图形、大小、颜色。", "index": 10, "solutions": [1], "options": ["错误", "正确"]}, {"type": 1, "info": "定向地图上的等高线，高山，小丘、主干道及坚硬的路面用棕色来表示。", "index": 11, "solutions": [1], "options": ["错误", "正确"]}, {"type": 1, "info": "身体疲劳时也可进行专门性柔韧性训练。（    ）", "index": 12, "solutions": [0], "options": ["错误", "正确"]}, {"type": 1, "info": "芨芨草指示地下水位于地表下1m左右，芦苇指示地下水位只有1m左右。（    ）", "index": 13, "solutions": [0], "options": ["错误", "正确"]}, {"type": 1, "info": "掷实心球的丈量方法是从起掷线前缘至球着地点的后缘之间的距离。（）", "index": 14, "solutions": [0], "options": ["错误", "正确"]}, {"type": 1, "info": "蛙泳每次转身和到达终点时，两手应在水面、水上或水下触壁。（）", "index": 15, "solutions": [0], "options": ["错误", "正确"]}, {"type": 1, "info": "体育运动只是对促进人的体质健康有价值。", "index": 16, "solutions": [0], "options": ["错误", "正确"]}, {"type": 1, "info": "我国高校体育的首要任务是造就骨干，指导普及", "index": 17, "solutions": [0], "options": ["错误", "正确"]}, {"type": 1, "info": "100米个人混合泳、4×50米自由泳接力只限于25米池。", "index": 18, "solutions": [1], "options": ["错误", "正确"]}, {"type": 1, "info": "体育竞赛对学生心理健康的促进作用表现在克服学生遇事紧张的心态，培养沉着冷静的良好心态（ ）", "index": 19, "solutions": [1], "options": ["错误", "正确"]}, {"type": 1, "info": "娱乐性体育活动对大学生心理健康的促进作用表现在启发学生思维、提高创新能力、培养活泼愉快的个性有着积极的作用。（ ）", "index": 20, "solutions": [1], "options": ["错误", "正确"]}, {"type": 1, "info": "应在营地的下风口建厕所 。（    ）", "index": 21, "solutions": [1], "options": ["错误", "正确"]}, {"type": 1, "info": "溯溪和溪降都要检查天气情况（    ）", "index": 22, "solutions": [1], "options": ["错误", "正确"]}, {"type": 1, "info": "北京2008年奥运吉祥物福娃“晶晶”，原型为燕子。", "index": 23, "solutions": [0], "options": ["错误", "正确"]}, {"type": 1, "info": "保持平稳、避免冲撞是漂流过程中需恪守的原则。（    ）", "index": 24, "solutions": [1], "options": ["错误", "正确"]}, {"type": 2, "options": ["它是三面标志旗连接成的三棱体", "每面点标旗上部为白色，右下部为橙红色", "每面点标旗尺寸为30厘米*30厘米", "每面点标旗为40厘米*40厘米"], "info": "对点标旗的正确描述不正确的（_____ ）", "index": 25, "solutions": [3]}, {"type": 2, "options": ["500", "2000", "5000", "10000"], "info": "游泳距今已经有_____多年的发展历史。", "index": 26, "solutions": [2]}, {"type": 2, "options": ["小河", "高墙", "道路", "树"], "info": "线状地物符号不表示（_____ ）", "index": 27, "solutions": [3]}, {"type": 2, "options": ["缓、高", "缓、低", "陡、高", "陡、低"], "info": "在同一地图上等高线间距大则坡_______,等高线多则山_________。", "index": 28, "solutions": [0]}, {"type": 2, "options": ["水平位移法", "偏向瞄准法", "借线法", "步测法"], "info": "我们有意识地将目标方向往左或往右移一定角度后，就非常明确检查点的位置，这种是__________方法。", "index": 29, "solutions": [0]}, {"type": 2, "options": ["黄色", "绿色", "白色", "蓝色"], "info": "湖泊、溪流、沼泽用______颜色表示。", "index": 30, "solutions": [3]}, {"type": 2, "options": ["绿色", "白色", "黄色", "蓝色"], "info": "空旷地区用_______颜色表示。", "index": 31, "solutions": [2]}, {"type": 2, "options": ["黄色", "棕色", "白色", "绿色"], "info": "通透易通过树林用______颜色表示。", "index": 32, "solutions": [2]}, {"type": 2, "options": ["小河", "高墙", "道路", "树木"], "info": "以下不属于线状地物符号的是___________。", "index": 33, "solutions": [3]}, {"type": 2, "options": ["利用植物判定方位", "利用凹入地物判定方位", "利用阴影方向变化判定方位", "利用季风判定方位"], "info": "利用地物特征判定方位不包括________。", "index": 34, "solutions": [2]}, {"type": 2, "options": ["扶手法", "攻击点法", "偏向瞄准法", "水平位移法"], "info": "行进前，先要将途中参照物辨认清楚，然后用最快的速度前往检查点的选择路线方法是___________。", "index": 35, "solutions": [1]}, {"type": 2, "options": ["坏血病", "佝偻病", "心脏病", "水肿"], "info": "缺乏维生素C、会引起的疾病是，（　　）", "index": 36, "solutions": [0]}, {"type": 2, "options": ["冲撞", "搁浅", "落水", "气室破裂"], "info": "漂流时，最糟糕的情况是遇到（ ）", "index": 37, "solutions": [3]}, {"type": 2, "options": ["3500", "4000", "4500", "5000"], "info": "我国青藏高原雪线一般在（ ）为左右。", "index": 38, "solutions": [2]}, {"type": 2, "options": ["罗雪娟", "庄泳", "乐靖宜", "杨文意"], "info": "中国第一枚奥运会游泳金牌获得者是？", "index": 39, "solutions": [1]}, {"type": 2, "options": ["茜尼斯卡", "欧文斯", "科洛巴斯", "刘易斯"], "info": "以杰出的运动才能和辉煌成就粉碎了纳粹分子的优等种族美梦的是", "index": 40, "solutions": [1]}, {"type": 2, "options": ["中上强度", "中等强度", "大强度", "小强度"], "info": "以健身为目标的耐力性运动，通常采用", "index": 41, "solutions": [1]}, {"type": 2, "options": ["教育部门", "体育部门", "文化部门", "卫生部门"], "info": "学生体质监测由国务院（）部门组织实施", "index": 42, "solutions": [0]}, {"type": 2, "options": ["鼻炎患者", "四肢容易抽搐者", "近视眼患者", "癫痫病人"], "info": "下列严格禁止下水游泳的人群是", "index": 43, "solutions": [3]}, {"type": 2, "options": ["植物生命", "自然生命", "社会生命", "精神生命"], "info": "下列哪一项不是人生命的维度之一", "index": 44, "solutions": [0]}, {"type": 2, "options": ["①②③", "①③④", "②③⑤", "③④⑤"], "info": "为进一步提高短跑能力，小王希望在家中也能进行有针对性的练习。下列对他有明显帮助的是___①手扶卧室墙,练习单脚支撑蹲立??②在客厅里练习太极拳?③在客厅里练习弓箭步走 ④在阳台上练习摆臂 ，动作由慢到快?⑤在卧室里练习前滚翻?", "index": 45, "solutions": [1]}, {"type": 2, "options": ["10~20秒", "20~40秒", "30~50", "60秒以上"], "info": "投掷力量训练时，练习靠墙倒立和倒立推起。练习者先学习手倒立，平衡保持___", "index": 46, "solutions": [2]}, {"type": 2, "options": ["2米/秒", "4米/秒", "6米/秒", "8米/秒"], "info": "涉水渡河要选择河水比较浅，水流平缓，无暗礁、暗流和漩涡的地点，如果水深过腰、水流速度超过___，则不要无保护地涉水渡河。", "index": 47, "solutions": [1]}, {"type": 2, "options": ["卡特尔", "陈会昌", "艾森克", "以上都不是"], "info": "常用的心理健康测量表中气质测量表是由（）编制的，包括四种类型。", "index": 48, "solutions": [1]}, {"type": 2, "options": ["横轴", "纵切面", "垂直轴", "纵轴"], "info": "根据人体在水中的运动方向，贯穿身体上下方向的轴叫做 _____ 轴？", "index": 49, "solutions": [2]}, {"type": 3, "options": ["跳入法", "爬入法", "滑入法", "步入法"], "info": "在救护过程中，为了确保救护人员的人身安全，可采用_____ 法入水。", "index": 50, "solutions": [0, 1, 2, 3]}], "sn": "8165065f52b9bbf9"}