{"course": {"name": "跆拳道", "id": 13}, "topics": [{"type": 1, "info": "从两耳向前的头颈的前部，只允许用拳的技术攻击", "index": 1, "solutions": [0], "options": ["错误", "正确"]}, {"type": 1, "info": "一个人学过体育心理学，就可以说明自己一定在体育教学或指导运动队方面取得成功", "index": 2, "solutions": [0], "options": ["错误", "正确"]}, {"type": 1, "info": "夏季奥运会和冬季奥会必须在同一城市举行", "index": 3, "solutions": [0], "options": ["错误", "正确"]}, {"type": 1, "info": "体育运动只是对促进人的体质健康有价值", "index": 4, "solutions": [0], "options": ["错误", "正确"]}, {"type": 1, "info": "课间活动或课间操，主要指文化课下课后，在教室周围进行的激烈活动，课间活动的主要意义是通过活动，消除上课产生的疲劳，便于休息", "index": 5, "solutions": [0], "options": ["错误", "正确"]}, {"type": 1, "info": "对于月经初潮不久的女子运动员月经期参加体育比赛，可采用“人工月经周期”来调整月经期，使其错开比赛期", "index": 6, "solutions": [0], "options": ["错误", "正确"]}, {"type": 1, "info": "溯溪是源于欧洲阿尔卑斯山的一种登山方式，可以结合登山、游泳、野外求生等综合性技术的户外活动", "index": 7, "solutions": [1], "options": ["错误", "正确"]}, {"type": 1, "info": "体育竞赛对学生心理健康的促进作用表现在克服自负逞强，树立“山外有山，人外有人”的平和心态", "index": 8, "solutions": [1], "options": ["错误", "正确"]}, {"type": 1, "info": "跆拳道的独特之处在于，它对训练者的性格塑造、毅力、韧性、技术水平以及个人潜能进行评定划级", "index": 9, "solutions": [1], "options": ["错误", "正确"]}, {"type": 1, "info": "生活方式主要由生活主体、生活资料、生活时间、生活空间所组成", "index": 10, "solutions": [1], "options": ["错误", "正确"]}, {"type": 1, "info": "法特莱克法是斯堪地那维亚人发明的一种利用地形、地貌或认为设置的加速与减速段落来发展耐力的方法", "index": 11, "solutions": [1], "options": ["错误", "正确"]}, {"type": 1, "info": "通常把出发技术划分为预备姿势、起跳、腾空和入水、滑行和开始游泳等五个阶段", "index": 12, "solutions": [1], "options": ["错误", "正确"]}, {"type": 1, "info": "肌肉痉挛是指肌肉发生不自主的强直收缩，引起局部疼痛和活动障碍", "index": 13, "solutions": [1], "options": ["错误", "正确"]}, {"type": 1, "info": "每场比赛开始前30分钟开始点名，共点名3次，比赛开始后1分钟仍未到场者，按自动弃权论", "index": 14, "solutions": [1], "options": ["错误", "正确"]}, {"type": 1, "info": "垫步的操作方法：右架站立，右脚向左脚内侧上步时，左腿迅速提起，身体重心在空中", "index": 15, "solutions": [0], "options": ["错误", "正确"]}, {"type": 1, "info": "以左右不同式实战站位相对叫开式站位", "index": 16, "solutions": [1], "options": ["错误", "正确"]}, {"type": 1, "info": "良好的柔韧性可使用动作更加到位，并减少运动员损伤的发生", "index": 17, "solutions": [1], "options": ["错误", "正确"]}, {"type": 1, "info": "赛前一小时称量体重，不合格不得参加该级别比赛", "index": 18, "solutions": [0], "options": ["错误", "正确"]}, {"type": 1, "info": "运用生动的语言进行启发式教学，通过讲解、口令、提示、要求、指示、比喻、复诵、反问、提问等促使学生积极思维，加深对教学内容的理解都属于教学直观性范畴", "index": 19, "solutions": [1], "options": ["错误", "正确"]}, {"type": 1, "info": "跆拳道品势的修练境界可分为型、意、实用、自我流、完善", "index": 20, "solutions": [1], "options": ["错误", "正确"]}, {"type": 1, "info": "开立步是指两脚开立与肩同宽，身体自然直立，两膝微屈，两脚尖正对前方，两臂垂于体侧", "index": 21, "solutions": [0], "options": ["错误", "正确"]}, {"type": 1, "info": "使用电子护具时，设1名主裁判和3名副裁判", "index": 22, "solutions": [0], "options": ["错误", "正确"]}, {"type": 1, "info": "初学者从十级开始至一级，然后再入段", "index": 23, "solutions": [1], "options": ["错误", "正确"]}, {"type": 1, "info": "培养优良的思想和道德品质，以及勇猛顽强的意志品质，也是跆拳道教学的基本任务之一", "index": 24, "solutions": [1], "options": ["错误", "正确"]}, {"type": 2, "options": ["窒息", "心力衰竭", "血流不止", "A和B"], "info": "中神经毒的病，最后因（ ）而危及生命", "index": 25, "solutions": [3]}, {"type": 2, "options": ["跳跃运动员", "短跑运动员", "投掷运动员", "长跑运动员"], "info": "慢肌纤维占优势是哪类运动的特点？", "index": 26, "solutions": [3]}, {"type": 2, "options": ["每周进行3次体育运动", "每天步行3公里", "每3天步行一次", "每3天进行一次运动"], "info": "我国相关学者提出的“三、五、七”运动方式中的“三”是指（ ）？", "index": 27, "solutions": [1]}, {"type": 2, "options": ["100米", "马拉松", "20公里竞走", "三级跳远"], "info": "下列属于田径比赛中田赛项目的是", "index": 28, "solutions": [3]}, {"type": 2, "options": ["大力挣扎", "保持冷静，示意救生员或周围同伴施救", "尽全力游向岸边", "以上都不对"], "info": "游泳过程中发生小腿肌肉痉挛时应该", "index": 29, "solutions": [1]}, {"type": 2, "options": ["运动量和时间", "运动强度、时间、密度", "运动强度、时间、频率", "运动强度和次数"], "info": "制定运动处方的内容包括确定目标，选择运动项目，确定", "index": 30, "solutions": [1]}, {"type": 2, "options": ["罗雪娟", "庄泳", "乐靖宜", "杨文意"], "info": "中国第一枚奥运会游泳金牌获得者是？", "index": 31, "solutions": [1]}, {"type": 2, "options": ["3：1", "2：1", "4：1", "5：1"], "info": "在生死关头，在严格的控制下才能喝海水，一般以 海水:淡水（ ）的比例掺合饮用", "index": 32, "solutions": [1]}, {"type": 2, "options": ["靠近底部", "中部", "靠近上部", "拎在手上"], "info": "填装背包时，帐篷一般放在背包的（ ），行军时比较舒适", "index": 33, "solutions": [2]}, {"type": 2, "options": ["东方", "西方", "南方", "北方"], "info": "农历初五以前的月亮,在黄昏后会出现在天空的", "index": 34, "solutions": [1]}, {"type": 2, "options": ["心理恢复", "合理安排", "积极性休息"], "info": "为了有效地消除疲劳而采用自我暗示，放松训练，旅游，听音乐等手段，简称", "index": 35, "solutions": [0]}, {"type": 2, "options": ["一方运动员的双脚是否越出边界线", "双方运动员的两脚是否越出边界线", "主裁喊“分开”的时间先后", "使用技术的一方两脚是否越出边界线"], "info": "边裁判衡量运动员在越出边界线时使用技术是否有效的主要依据是 (_____).", "index": 36, "solutions": [3]}, {"type": 2, "options": ["S", "V", "M", "L"], "info": "动作周期是指一个完整动作所用的时间，一般用 _____ 符号来表示？", "index": 37, "solutions": [0]}, {"type": 2, "options": ["3", "4", "5", "6"], "info": "在雅典奥运会上，美国的菲尔普斯共获得_____ 金牌", "index": 38, "solutions": [2]}, {"type": 2, "options": ["感应", "达到力度", "感应并达到力度"], "info": "运动员穿电子脚套使用技术击打到电子护具，显示得分的原理是", "index": 39, "solutions": [2]}, {"type": 2, "options": ["接触行为", "不当行为", "攻击行为", "消极行为"], "info": "跆拳道实战中用膝部顶撞对手；故意攻击对手裆部；故意蹬踏对手的腿部和脚等属判罚警告与判罚扣分犯规行为中的", "index": 40, "solutions": [2]}, {"type": 2, "options": ["主裁判", "副裁判", "裁判长"], "info": "跆拳道比赛场上裁判员组成没有？", "index": 41, "solutions": [2]}, {"type": 2, "options": ["不计", "要计", "可以商量"], "info": "规则规定警告两次扣1分，比赛结束时警告次数为奇数，最后一次应", "index": 42, "solutions": [0]}, {"type": 2, "options": ["1", "2", "3"], "info": "竞赛规则规定警告和扣分按（_____ ）局累计", "index": 43, "solutions": [2]}, {"type": 2, "options": ["5", "7", "10"], "info": "冷水擦身的开始阶段，时间一般不超过（_____ ）分钟", "index": 44, "solutions": [0]}, {"type": 2, "options": ["树木繁茂的江河边", "饭后半小时内", "人口稀少的空旷地"], "info": "空气浴禁忌以下事项中的哪一条", "index": 45, "solutions": [1]}, {"type": 2, "options": ["4", "8", "10"], "info": "全国跆拳道锦标赛男女各有（_____ ）级别", "index": 46, "solutions": [1]}, {"type": 2, "options": ["2", "3", "4"], "info": "比赛中，使用后踢击中对方面部得（_____ ）分", "index": 47, "solutions": [2]}, {"type": 2, "options": ["耐力素质训练", "有氧素质训练", "速度素质训练"], "info": "各种形式的长时间跑、球类运动、游泳、跳绳、连续的踢击脚靶练习，被称之为", "index": 48, "solutions": [0]}, {"type": 2, "options": ["拳法", "手法", "指法"], "info": "在跆拳道品势中，拳、掌、指，通称为", "index": 49, "solutions": [1]}, {"type": 3, "options": ["踝关节", "髋关节", "腰部", "肩关节"], "info": "游泳运动员最柔软的关节是", "index": 50, "solutions": [0, 3]}], "sn": "14da0cf8aa452b8e"}