{"course": {"name": "乒乓球", "id": 16}, "topics": [{"type": 1, "info": "动作周期是指一个完整动作所用的时间，一般用“V”来表示。", "index": 1, "solutions": [0], "options": ["错误", "正确"]}, {"type": 1, "info": "脸部擦伤处理时不宜使用龙胆紫外涂", "index": 2, "solutions": [1], "options": ["错误", "正确"]}, {"type": 1, "info": "持续训练法是有氧代谢能力跑的一种练习方法。( )", "index": 3, "solutions": [1], "options": ["错误", "正确"]}, {"type": 1, "info": "动力性力量训练是户外运动及训练不可缺少的练习。（    ）", "index": 4, "solutions": [1], "options": ["错误", "正确"]}, {"type": 1, "info": "溪降时的着装应以具伸缩性大的运动裤或游泳衣裤为主（    ）", "index": 5, "solutions": [1], "options": ["错误", "正确"]}, {"type": 1, "info": "晨脉应在运动员早晨醒来起床后安静的状态下测定", "index": 6, "solutions": [0], "options": ["错误", "正确"]}, {"type": 1, "info": "投掷项目助跑的目的是为了身体在器械出手前有一个良好的姿势（）", "index": 7, "solutions": [0], "options": ["错误", "正确"]}, {"type": 1, "info": "在测试皮褶厚度的时候，男生和女生通用一个部位进行测量。（）", "index": 8, "solutions": [0], "options": ["错误", "正确"]}, {"type": 1, "info": "掷实心球的丈量方法是从起掷线前缘至球着地点的后缘之间的距离。（）", "index": 9, "solutions": [0], "options": ["错误", "正确"]}, {"type": 1, "info": "溪降不用戴安全帽。(     )", "index": 10, "solutions": [0], "options": ["错误", "正确"]}, {"type": 1, "info": "人的主动柔韧性总是好于人的被动柔韧性（    ）", "index": 11, "solutions": [0], "options": ["错误", "正确"]}, {"type": 1, "info": "乒乓球比赛首先是从发球和接发球开始，比赛中接发球技术差就会造成被动，导致心理上紧张和畏惧，引起一连串失误。", "index": 12, "solutions": [1], "options": ["错误", "正确"]}, {"type": 1, "info": "如果比赛中球损坏，应由比赛前选定的另外一个球代替。", "index": 13, "solutions": [1], "options": ["错误", "正确"]}, {"type": 1, "info": "从抛球前球静止的最后一瞬间到击球时，球和球拍应在比赛台面的水平面之上。", "index": 14, "solutions": [1], "options": ["错误", "正确"]}, {"type": 1, "info": "关节韧带扭伤后，应立即进行冷敷或加压包扎、抬高伤肢。", "index": 15, "solutions": [0], "options": ["错误", "正确"]}, {"type": 1, "info": "比赛台面包括球台台面的侧面。", "index": 16, "solutions": [0], "options": ["错误", "正确"]}, {"type": 1, "info": "球网装置包括球网、悬网绳、网柱及将它们固定在球台上的夹钳部分。", "index": 17, "solutions": [1], "options": ["错误", "正确"]}, {"type": 1, "info": "在同一场比赛中，如果运动员发球动作的正确性再次受到怀疑，不管是否出于同样的原因，不再警告而判失一分。", "index": 18, "solutions": [1], "options": ["错误", "正确"]}, {"type": 1, "info": "选择发球，接发球和这一方,那一方的权力应由抽签来决定，中签者可以选择先发球或先接发球，或选择先在某一方。", "index": 19, "solutions": [1], "options": ["错误", "正确"]}, {"type": 1, "info": "“国际竞赛”，即一个以上协会的运动员参加的比赛。", "index": 20, "solutions": [1], "options": ["错误", "正确"]}, {"type": 1, "info": "在局与局之间，不超过1分钟的休息时间。", "index": 21, "solutions": [1], "options": ["错误", "正确"]}, {"type": 1, "info": "弧圈球是由中国人发明的。", "index": 22, "solutions": [0], "options": ["错误", "正确"]}, {"type": 2, "options": ["高强度", "低强度", "中等偏上", "中等偏下"], "info": "（ ）运动量对女生有较好的心理健康效应", "index": 23, "solutions": [3]}, {"type": 2, "options": ["经济发展对健康起到促进作用", "经济发展对健康起到阻碍作用", "经济发展健康既有促进作用,又有阻碍作用?", "经济发展促进发达国家人群健康"], "info": "经济发展对健康的作用是?", "index": 24, "solutions": [2]}, {"type": 2, "options": ["10米", "15米", "20米", "25米"], "info": "田径运动会的4×100m 接力比赛中，每个接力区的有效距离是( )", "index": 25, "solutions": [0]}, {"type": 2, "options": ["奥斯佩丁", "顾拜旦", "韦尔", "洛克"], "info": "现代奥运会的创始人是？", "index": 26, "solutions": [1]}, {"type": 2, "options": ["18—20", "20—22", "20—25", "22--25"], "info": "一般来说，人到了（ ）岁，骺软骨就完全骨化，骨的长度不在增长", "index": 27, "solutions": [0]}, {"type": 2, "options": ["女足", "女排", "女子举重", "女篮"], "info": "中国体育健儿首次夺得金牌的集体项目是？", "index": 28, "solutions": [1]}, {"type": 2, "options": ["身体的姿势", "手臂动作、脚的动作", "手脚配合", "身体姿势、手臂动作、脚的动作、手脚配合"], "info": "攀岩技术主要取决于", "index": 29, "solutions": [3]}, {"type": 2, "options": ["东", "南", "西", "北"], "info": "利用凸出地物如墙、地埂、大石块等判定方向时，其向（ ）一侧的基部较潮湿，并可能生有苔类植物。", "index": 30, "solutions": [3]}, {"type": 2, "options": ["“8”字环", "抓结", "ATC", "GRIGRI"], "info": "下降器（ ）的随孔设计可以除去绳上的冰雪，尤其适合在冰雪环境中使用。", "index": 31, "solutions": [2]}, {"type": 2, "options": ["膨胀钉", "扁带", "拉片", "O型扣锁"], "info": "下列哪项不是建人工锚点时不需要的（ ）", "index": 32, "solutions": [1]}, {"type": 2, "options": ["38毫米", "40毫米", "42毫米"], "info": "现在乒乓球标准直径是：", "index": 33, "solutions": [1]}, {"type": 2, "options": ["200米蝶泳", "400米自由泳", "100米个人混合泳", "4×100米自由泳接力"], "info": "下列 _____ 是属于25米短池游泳比赛？", "index": 34, "solutions": [2]}, {"type": 2, "options": ["5米标志线", "4米标志线", "3米标志线", "2米标志线"], "info": "仰泳应为看不见是否接近池壁，运动员是依靠______来判断触壁距离的。", "index": 35, "solutions": [0]}, {"type": 2, "options": ["1988年", "1989年", "1990年"], "info": "乒乓球比赛在哪年正式列入奥运会比赛项目：", "index": 36, "solutions": [0]}, {"type": 2, "options": ["失一分", "得一分", "重发"], "info": "对方运动员用不符合规定的拍面击球应判：对方", "index": 37, "solutions": [0]}, {"type": 2, "options": ["中部", "上部", "中下部"], "info": "要发出正手下旋球，应接触球的哪一部位：", "index": 38, "solutions": [2]}, {"type": 2, "options": ["离开发球员手掌后，至少垂直上升16厘米", "上升球不能超过90厘米", "离开发球员手掌后，至少垂直上升16厘米以上", "所升高度不限，垂直上升就行"], "info": "发球时，球被抛起高度不得低于：", "index": 39, "solutions": [0]}, {"type": 2, "options": ["1.5米", "1.25米", "1.525米", "1.83米"], "info": "乒乓球台宽度是:", "index": 40, "solutions": [2]}, {"type": 2, "options": ["6分制", "7分制", "11分制", "21分制"], "info": "当今乒乓球正式比赛实行几分制：", "index": 41, "solutions": [2]}, {"type": 2, "options": ["6", "5", "4", "7"], "info": "在比赛中，双方得分相加是几分的倍数才允许擦汗：", "index": 42, "solutions": [0]}, {"type": 2, "options": ["判A得分,因为X发球失误", "判重发球,因为A在发球擦网时阻挡了球", "判重发球,因为A的不执拍手触及比赛台面", "判X得分,因为A阻挡来球"], "info": "比赛中,X发球,球在本台区弹起,触到网柱后高高弹起,到A方台区上空,球降落时,A用不执拍手接住了球,然后把手放在比赛台面上，判：", "index": 43, "solutions": [1]}, {"type": 2, "options": ["东边", "西边", "根据第四局的站位来推算", "请裁判员决定"], "info": "第一局一开始，A站在东边，第三、第四局X站在西边，第五局一开始，A应该站：", "index": 44, "solutions": [0]}, {"type": 3, "options": ["黑色", "绿色", "橙色", "红色"], "info": "乒乓球规则规定乒乓球拍的两面分别是什么颜色？", "index": 45, "solutions": [0, 3]}, {"type": 3, "options": ["左、右半区又称1/2区", "近网区指距球网40厘米以内的区域", "台外区，有称界外区", "底线区指距端线30厘米以内的区域"], "info": "比赛台面的区域可分为?", "index": 46, "solutions": [0, 1, 3]}, {"type": 3, "options": ["直接越过或绕过球网装置", "用不执拍手击球过网", "只要能将球击过球网", "触及球网装置后，再触及对方台区"], "info": "对方发球或还击后，本方运动员必须击球，使球？", "index": 47, "solutions": [0, 3]}, {"type": 3, "options": ["乒乓球由直径38毫米、重量2.5克,改为40毫米、2.7克", "乒乓球比赛由每局21分改为11分", "乒乓球的颜色由白色改为橙色", "乒乓球比赛执行无遮挡发球"], "info": "自20世纪末开始,国际乒联对乒乓球运动进行了一系列的改革,它们是?", "index": 48, "solutions": [0, 1, 3]}, {"type": 3, "options": ["50米、100米、200米（短距离）", "25米、50米、100米（短距离）", "400米、1500米、3000米（中长距离）", "400米、800米、1500米（中长距离）"], "info": "“奥运会”所设各种游泳比赛的距离有：_____ 。", "index": 49, "solutions": [0, 3]}, {"type": 3, "options": ["对方阻挡", "裁判员或副裁判员暂停比赛", "对方不执拍手触及比赛台面", "由于发生了运动员无法控制的干扰,而使运动员未能合法发球,合法还击或遵守规则"], "info": "回合出现下列哪些情况应判重发球?", "index": 50, "solutions": [1, 3]}], "sn": "3b56f56a21debefb"}